kritapy/__init__.py
kritapy/document.py
kritapy/layers/__init__.py
kritapy/layers/base.py
kritapy/layers/paint.py
kritapy/layers/shape.py
kritapy/layers/text.py
kritapy/styles/__init__.py
kritapy/styles/asl.py
kritapy/styles/layer.py
kritapy/styles/text.py
kritapy/utils/__init__.py
kritapy/utils/compression.py
kritapy/utils/xml.py
kritapy-0.0.0.dist-info/METADATA
kritapy-0.0.0.dist-info/WHEEL
kritapy-0.0.0.dist-info/top_level.txt
kritapy-0.0.0.dist-info/RECORD
