Metadata-Version: 2.2
Name: kritapy
Version: 0.0.0
Summary: Python library for creating and manipulating Krita documents programmatically
License: MIT
Project-URL: Homepage, https://github.com/cozy-creator/kritapy
Project-URL: Repository, https://github.com/cozy-creator/kritapy.git
Project-URL: Issues, https://github.com/cozy-creator/kritapy/issues
Keywords: krita,image,graphics,digital art
Classifier: Development Status :: 3 - Alpha
Classifier: Intended Audience :: Developers
Classifier: Topic :: Multimedia :: Graphics
Classifier: License :: OSI Approved :: MIT License
Classifier: Programming Language :: Python :: 3
Classifier: Programming Language :: Python :: 3.8
Classifier: Programming Language :: Python :: 3.9
Classifier: Programming Language :: Python :: 3.10
Classifier: Programming Language :: Python :: 3.11
Requires-Python: >=3.8
Requires-Dist: Pillow>=9.0.0
Requires-Dist: numpy>=1.20.0
Requires-Dist: python-lzf>=0.2.4
